{
  "time": "2026-06-26 23:40:03",
  "results": [
    {
      "symbol": "AAVEUSDT",
      "trend": "strong_long",
      "score": 9,
      "signals": [
        "15m多头排列",
        "1h多头排列",
        "4h多头排列",
        "超买区(RSI15m=72,1h=82)",
        "接近阻力(+0.3%)",
        "强势上涨(15m+3.9%,1h+6.5%)"
      ],
      "rsi_15m": 72.08374875373872,
      "rsi_1h": 82.28571428571426,
      "vol_ratio": 1.1424596637285973,
      "momentum_15m": 3.9006690100918444,
      "momentum_1h": 6.459858254908799
    },
    {
      "symbol": "ETHUSDT",
      "trend": "short",
      "score": -3,
      "signals": [
        "15m多头排列",
        "4h空头排列",
        "接近阻力(+0.1%)"
      ],
      "rsi_15m": 66.92813765182188,
      "rsi_1h": 55.85561011092927,
      "vol_ratio": 0.7023816294667529,
      "momentum_15m": 1.79561115642238,
      "momentum_1h": 3.2106596505395575
    },
    {
      "symbol": "DOGEUSDT",
      "trend": "short",
      "score": -3,
      "signals": [
        "15m多头排列",
        "4h空头排列",
        "接近阻力(+0.2%)"
      ],
      "rsi_15m": 65.39855072463767,
      "rsi_1h": 56.02910602910601,
      "vol_ratio": 0.7654878068521084,
      "momentum_15m": 1.6779431664411437,
      "momentum_1h": 2.49624880643841
    },
    {
      "symbol": "XRPUSDT",
      "trend": "short",
      "score": -3,
      "signals": [
        "15m多头排列",
        "4h空头排列",
        "接近阻力(+0.6%)"
      ],
      "rsi_15m": 67.74691358024704,
      "rsi_1h": 55.93354430379743,
      "vol_ratio": 0.7341791875554831,
      "momentum_15m": 0.7510832932113654,
      "momentum_1h": 2.6690216858012086
    },
    {
      "symbol": "NEARUSDT",
      "trend": "strong_short",
      "score": -7,
      "signals": [
        "1h空头排列",
        "4h空头排列"
      ],
      "rsi_15m": 56.08974358974356,
      "rsi_1h": 50.207336523125974,
      "vol_ratio": 0.7834063918030344,
      "momentum_15m": 1.5662718239487907,
      "momentum_1h": 1.686245854645609
    }
  ]
}